tradion_api_client/__init__.py
tradion_api_client/config.py
tradion_api_client/exceptions.py
tradion_api_client/core/__init__.py
tradion_api_client/core/interactive.py
tradion_api_client/core/market_data.py
tradion_api_client/utils/__init__.py
tradion_api_client/utils/http_client.py
tradion_api_client/utils/logger.py
tradion_api_client-0.2.0.dist-info/METADATA
tradion_api_client-0.2.0.dist-info/WHEEL
tradion_api_client-0.2.0.dist-info/RECORD
