Metadata-Version: 2.4
Name: tradion_api_client
Version: 0.2.0
Summary: tradion api client
Requires-Python: >=3.13
Requires-Dist: aiohttp>=3.11.11
Requires-Dist: ipykernel>=7.1.0
Requires-Dist: websockets>=15.0.1
Requires-Dist: xts-api-client>=0.1.19
